ruffle/__init__.py
ruffle/benchmarks.py
ruffle/dataloaders.py
ruffle/models.py
ruffle/predictor.py
ruffle/schedulers.py
ruffle/setup.py
ruffle/trainer.py
ruffle/types.py
ruffle/utils.py
ruffle-0.0.1a3.dist-info/METADATA
ruffle-0.0.1a3.dist-info/WHEEL
ruffle-0.0.1a3.dist-info/entry_points.txt
ruffle-0.0.1a3.dist-info/RECORD
