Metadata-Version: 2.4
Name: ruffle
Version: 0.0.1a3
Requires-Python: >=3.13
Requires-Dist: datasets>=4.0.0
Requires-Dist: jsonargparse[signatures]>=4.40.0
Requires-Dist: lightning>=2.5.3
Requires-Dist: rich>=14.1.0
Requires-Dist: tensorboard>=2.20.0
Requires-Dist: transformers>=4.55.2
